{"totalErReceived": 100.0, "information": {"machineId": "29040017", "location": "REGION I, ILOCOS SUR, BURGOS, MAMBUG", "votingCenter": "MAMBUG, BURGOS, ILOCOS SUR", "precinctId": "29040017", "precinctInCluster": "0032A, 0032B, 0033A", "abstentions": 0, "numberOfRegisteredVoters": 443, "numberOfActuallyVoters": 392, "numberOfValidBallot": 392, "turnout": 88.49}, "national": [{"contestCode": "00399000", "contestName": "SENATOR of PHILIPPINES", "statistic": {"overVotes": 24, "underVotes": 2499, "validVotes": 5316, "obtainedVotes": 2181}, "candidates": {"candidates": [{"name": "1. ABALOS, BENHUR (PFP)", "votes": 138, "percentage": 6.33}, {"name": "2. ADONIS, JEROME (MKBYN)", "votes": 7, "percentage": 0.32}, {"name": "3. AMAD, WILSON (IND)", "votes": 2, "percentage": 0.09}, {"name": "4. ANDAMO, NARS ALYN (MKBYN)", "votes": 3, "percentage": 0.14}, {"name": "5. AQUINO, BAM (KNP)", "votes": 74, "percentage": 3.39}, {"name": "6. ARAMBULO, RONNEL (MKBYN)", "votes": 12, "percentage": 0.55}, {"name": "7. ARELLANO, ERNESTO (KTPNAN)", "votes": 4, "percentage": 0.18}, {"name": "8. BALLON, ROBERTO (IND)", "votes": 12, "percentage": 0.55}, {"name": "9. BINAY, ABBY (NPC)", "votes": 86, "percentage": 3.94}, {"name": "10. BONDOC, JIMMY (PDPLBN)", "votes": 10, "percentage": 0.46}, {"name": "11. BONG REVILLA,RAMON, JR.(LAKAS)", "votes": 79, "percentage": 3.62}, {"name": "12. BOSITA, COLONEL (IND)", "votes": 74, "percentage": 3.39}, {"name": "13. BROSAS, ARLENE (MKBYN)", "votes": 14, "percentage": 0.64}, {"name": "14. CABONEGRO, ROY (DPP)", "votes": 1, "percentage": 0.05}, {"name": "15. CAPUYAN, ALLEN (PPP)", "votes": 1, "percentage": 0.05}, {"name": "16. CASI\u00d1O, TEDDY (MKBYN)", "votes": 14, "percentage": 0.64}, {"name": "17. CASTRO, TEACHER FRANCE (MKBYN)", "votes": 11, "percentage": 0.5}, {"name": "18. CAYETANO, PIA (NP)", "votes": 90, "percentage": 4.13}, {"name": "19. D'ANGELO, DAVID (BUNYOG)", "votes": 1, "percentage": 0.05}, {"name": "20. DE ALBAN,ATTORNEY ANGELO (IND)", "votes": 11, "percentage": 0.5}, {"name": "21. DE GUZMAN, KA LEODY (PLM)", "votes": 10, "percentage": 0.46}, {"name": "22. DELA ROSA, BATO (PDPLBN)", "votes": 35, "percentage": 1.6}, {"name": "23. DORINGO, NANAY MIMI (MKBYN)", "votes": 3, "percentage": 0.14}, {"name": "24. ESCOBAL, ARNEL (PM)", "votes": 5, "percentage": 0.23}, {"name": "25. ESPIRITU, LUKE (PLM)", "votes": 25, "percentage": 1.15}, {"name": "26. FLORANDA, MODY PISTON (MKBYN)", "votes": 5, "percentage": 0.23}, {"name": "27. GAMBOA, MARC LOUIE (IND)", "votes": 2, "percentage": 0.09}, {"name": "28. GO, BONG GO    (PDPLBN)", "votes": 73, "percentage": 3.35}, {"name": "29. GONZALES, NORBERTO (PDSP)", "votes": 6, "percentage": 0.28}, {"name": "30. HINLO, JAYVEE (PDPLBN)", "votes": 5, "percentage": 0.23}, {"name": "31. HONASAN, GRINGO (RP)", "votes": 31, "percentage": 1.42}, {"name": "32. JOSE, RELLY JR. (KBL)", "votes": 3, "percentage": 0.14}, {"name": "33. LACSON, PING (IND)", "votes": 108, "percentage": 4.95}, {"name": "34. LAMBINO,  RAUL  (PDPLBN)", "votes": 7, "percentage": 0.32}, {"name": "35. LAPID, LITO (NPC)", "votes": 93, "percentage": 4.26}, {"name": "36. LEE, MANOY WILBERT (AKSYON)", "votes": 2, "percentage": 0.09}, {"name": "37. LIDASAN, AMIRAH (MKBYN)", "votes": 3, "percentage": 0.14}, {"name": "38. MARCOLETA, RODANTE (IND)", "votes": 37, "percentage": 1.7}, {"name": "39. MARCOS, IMEE R. (NP)", "votes": 181, "percentage": 8.3}, {"name": "40. MARQUEZ, NORMAN (IND)", "votes": 8, "percentage": 0.37}, {"name": "41. MARTINEZ, ERIC (IND)", "votes": 6, "percentage": 0.28}, {"name": "42. MATA, DOC MARITES (IND)", "votes": 5, "percentage": 0.23}, {"name": "43. MATULA,  ATTY.  SONNY (WPP)", "votes": 10, "percentage": 0.46}, {"name": "44. MAZA, LIZA (MKBYN)", "votes": 9, "percentage": 0.41}, {"name": "45. MENDOZA, HEIDI (IND)", "votes": 30, "percentage": 1.38}, {"name": "46. MONTEMAYOR,  JOEY  (IND)", "votes": 0, "percentage": 0.0}, {"name": "47. MUSTAPHA, SUBAIR (WPP)", "votes": 1, "percentage": 0.05}, {"name": "48. OLIVAR, JOSE JESSIE (IND)", "votes": 3, "percentage": 0.14}, {"name": "49. ONG, DOC WILLIE (AKSYON)", "votes": 38, "percentage": 1.74}, {"name": "50. PACQUIAO, MANNY PACMAN (PFP)", "votes": 61, "percentage": 2.8}, {"name": "51. PANGILINAN, KIKO (LP)", "votes": 77, "percentage": 3.53}, {"name": "52. QUERUBIN,  ARIEL PORFIRIO (NP)", "votes": 21, "percentage": 0.96}, {"name": "53. QUIBOLOY, APOLLO (IND)", "votes": 6, "percentage": 0.28}, {"name": "54. RAMOS, DANILO (MKBYN)", "votes": 20, "percentage": 0.92}, {"name": "55. REVILLAME, WILLIE WIL (IND)", "votes": 46, "percentage": 2.11}, {"name": "56. RODRIGUEZ, ATTY. VIC (IND)", "votes": 11, "percentage": 0.5}, {"name": "57. SAHIDULLA, NUR-ANA (IND)", "votes": 0, "percentage": 0.0}, {"name": "58. SALVADOR, PHILLIP IPE (PDPLBN)", "votes": 21, "percentage": 0.96}, {"name": "59. SOTTO, TITO (NPC)", "votes": 138, "percentage": 6.33}, {"name": "60. TAPADO, MICHAEL BONGBONG (PM)", "votes": 2, "percentage": 0.09}, {"name": "61. TOLENTINO, FRANCIS TOL (PFP)", "votes": 41, "percentage": 1.88}, {"name": "62. TULFO, BEN BITAG (IND)", "votes": 107, "percentage": 4.91}, {"name": "63. TULFO, ERWIN (LAKAS)", "votes": 146, "percentage": 6.69}, {"name": "64. VALBUENA, MAR MANIBELA (IND)", "votes": 0, "percentage": 0.0}, {"name": "65. VERCELES, LEANDRO (IND)", "votes": 0, "percentage": 0.0}, {"name": "66. VILLAR, CAMILLE (NP)", "votes": 96, "percentage": 4.4}]}}, {"contestCode": "01199000", "contestName": "PARTY LIST of PHILIPPINES", "statistic": {"overVotes": 13, "underVotes": 54, "validVotes": 443, "obtainedVotes": 325}, "candidates": {"candidates": [{"name": "1 4PS", "votes": 5, "percentage": 1.54}, {"name": "2 PPP", "votes": 0, "percentage": 0.0}, {"name": "3 FPJ PANDAY BAYANIHAN", "votes": 0, "percentage": 0.0}, {"name": "4 KABATAAN", "votes": 2, "percentage": 0.62}, {"name": "5 DUTERTE YOUTH", "votes": 2, "percentage": 0.62}, {"name": "6 ML", "votes": 1, "percentage": 0.31}, {"name": "7 PBBM", "votes": 2, "percentage": 0.62}, {"name": "8 P3PWD", "votes": 0, "percentage": 0.0}, {"name": "9 MURANG KURYENTE", "votes": 1, "percentage": 0.31}, {"name": "10 BICOL SARO", "votes": 0, "percentage": 0.0}, {"name": "11 IPATUPAD", "votes": 0, "percentage": 0.0}, {"name": "12 PATROL", "votes": 0, "percentage": 0.0}, {"name": "13 JUAN PINOY", "votes": 0, "percentage": 0.0}, {"name": "14 ARTE", "votes": 0, "percentage": 0.0}, {"name": "15 WIFI", "votes": 0, "percentage": 0.0}, {"name": "16 MAAGAP", "votes": 0, "percentage": 0.0}, {"name": "17 UNITED SENIOR CITIZENS", "votes": 3, "percentage": 0.92}, {"name": "18 EPANAW SAMBAYANAN", "votes": 2, "percentage": 0.62}, {"name": "19 AKO PADAYON", "votes": 0, "percentage": 0.0}, {"name": "20 TUCP", "votes": 1, "percentage": 0.31}, {"name": "21 ACT TEACHERS", "votes": 3, "percentage": 0.92}, {"name": "22 1PACMAN", "votes": 0, "percentage": 0.0}, {"name": "23 TGP", "votes": 0, "percentage": 0.0}, {"name": "24 DUMPER PTDA", "votes": 0, "percentage": 0.0}, {"name": "25 ANAKALUSUGAN", "votes": 0, "percentage": 0.0}, {"name": "26 AKSYON DAPAT", "votes": 0, "percentage": 0.0}, {"name": "27 BHW", "votes": 2, "percentage": 0.62}, {"name": "28 SULONG DIGNIDAD", "votes": 0, "percentage": 0.0}, {"name": "29 BATANG QUIAPO", "votes": 1, "percentage": 0.31}, {"name": "30 PBA", "votes": 0, "percentage": 0.0}, {"name": "31 GILAS", "votes": 0, "percentage": 0.0}, {"name": "32 AKO ILOCANO AKO", "votes": 210, "percentage": 64.62}, {"name": "33 PAMILYANG MAGSASAKA", "votes": 1, "percentage": 0.31}, {"name": "34 CLICK PARTY", "votes": 0, "percentage": 0.0}, {"name": "35 ABANTE BISDAK", "votes": 0, "percentage": 0.0}, {"name": "36 MANILA TEACHERS", "votes": 0, "percentage": 0.0}, {"name": "37 PAMANA", "votes": 0, "percentage": 0.0}, {"name": "38 NANAY", "votes": 0, "percentage": 0.0}, {"name": "39 KM NGAYON NA", "votes": 0, "percentage": 0.0}, {"name": "40 BABAE AKO", "votes": 2, "percentage": 0.62}, {"name": "41 ARISE", "votes": 0, "percentage": 0.0}, {"name": "42 MAGDALO", "votes": 0, "percentage": 0.0}, {"name": "43 APEC", "votes": 0, "percentage": 0.0}, {"name": "44 MAGBUBUKID", "votes": 2, "percentage": 0.62}, {"name": "45 SSS-GSIS PENSYONADO", "votes": 0, "percentage": 0.0}, {"name": "46 GABRIELA", "votes": 0, "percentage": 0.0}, {"name": "47 TINGOG", "votes": 0, "percentage": 0.0}, {"name": "48 APAT-DAPAT", "votes": 0, "percentage": 0.0}, {"name": "49 AHON MAHIRAP", "votes": 0, "percentage": 0.0}, {"name": "50 UGB", "votes": 3, "percentage": 0.92}, {"name": "51 AKBAYAN", "votes": 4, "percentage": 1.23}, {"name": "52 AGIMAT", "votes": 0, "percentage": 0.0}, {"name": "53 PHILRECA", "votes": 1, "percentage": 0.31}, {"name": "54 KAPUSO PM", "votes": 0, "percentage": 0.0}, {"name": "55 ILOCANO DEFENDERS", "votes": 8, "percentage": 2.46}, {"name": "56 1-RIDER PARTY-LIST", "votes": 2, "percentage": 0.62}, {"name": "57 TICTOK", "votes": 0, "percentage": 0.0}, {"name": "59 BAYAN MUNA", "votes": 5, "percentage": 1.54}, {"name": "60 ANG PROBINSIYANO", "votes": 2, "percentage": 0.62}, {"name": "61 BANAT", "votes": 0, "percentage": 0.0}, {"name": "62 SBP", "votes": 0, "percentage": 0.0}, {"name": "63 BUHAY", "votes": 0, "percentage": 0.0}, {"name": "64 TULUNGAN TAYO", "votes": 0, "percentage": 0.0}, {"name": "65 SAGIP", "votes": 0, "percentage": 0.0}, {"name": "66 BTS BAYANING TSUPER", "votes": 0, "percentage": 0.0}, {"name": "67 VENDORS", "votes": 0, "percentage": 0.0}, {"name": "68 ACT-CIS", "votes": 7, "percentage": 2.15}, {"name": "69 AKTIBONG KAAGAPAY", "votes": 0, "percentage": 0.0}, {"name": "70 ASENSO PINOY", "votes": 0, "percentage": 0.0}, {"name": "71 SOLO PARENTS", "votes": 1, "percentage": 0.31}, {"name": "72 ANG KOMADRONA", "votes": 0, "percentage": 0.0}, {"name": "73 PROMDI", "votes": 0, "percentage": 0.0}, {"name": "74 PUSONG PINOY", "votes": 0, "percentage": 0.0}, {"name": "75 KUSUG TAUSUG", "votes": 0, "percentage": 0.0}, {"name": "76 DAMAYANG FILIPINO", "votes": 0, "percentage": 0.0}, {"name": "77 MPBL", "votes": 0, "percentage": 0.0}, {"name": "78 ANGAT", "votes": 0, "percentage": 0.0}, {"name": "79 KALINGA", "votes": 0, "percentage": 0.0}, {"name": "80 BOSES PARTY-LIST", "votes": 0, "percentage": 0.0}, {"name": "81 ARANGKADA PILIPINO", "votes": 0, "percentage": 0.0}, {"name": "82 AANGAT TAYO", "votes": 0, "percentage": 0.0}, {"name": "83 OFW", "votes": 0, "percentage": 0.0}, {"name": "84 BIDA KATAGUMPAY", "votes": 0, "percentage": 0.0}, {"name": "85 KAMANGGAGAWA", "votes": 0, "percentage": 0.0}, {"name": "86 BFF", "votes": 0, "percentage": 0.0}, {"name": "87 BUNYOG", "votes": 0, "percentage": 0.0}, {"name": "88 AGRI", "votes": 0, "percentage": 0.0}, {"name": "89 SENIOR CITIZENS", "votes": 2, "percentage": 0.62}, {"name": "90 4K", "votes": 0, "percentage": 0.0}, {"name": "91 PBP", "votes": 0, "percentage": 0.0}, {"name": "92 ONE COOP", "votes": 0, "percentage": 0.0}, {"name": "93 CIBAC", "votes": 0, "percentage": 0.0}, {"name": "94 BH - BAGONG HENERASYON", "votes": 0, "percentage": 0.0}, {"name": "95 1AGILA", "votes": 0, "percentage": 0.0}, {"name": "96 EDUAKSYON", "votes": 0, "percentage": 0.0}, {"name": "97 ANG TINIG NG SENIORS", "votes": 0, "percentage": 0.0}, {"name": "98 BG PARTY-LIST", "votes": 0, "percentage": 0.0}, {"name": "99 PINOY AKO", "votes": 0, "percentage": 0.0}, {"name": "100 H.E.L.P. PILIPINAS", "votes": 0, "percentage": 0.0}, {"name": "101 HEALTH WORKERS", "votes": 0, "percentage": 0.0}, {"name": "102 PEOPLE'S CHAMP", "votes": 0, "percentage": 0.0}, {"name": "103 AA-KASOSYO PARTY", "votes": 0, "percentage": 0.0}, {"name": "104 SOLID NORTH PARTY", "votes": 12, "percentage": 3.69}, {"name": "105 ABAMIN", "votes": 0, "percentage": 0.0}, {"name": "106 TRABAHO", "votes": 0, "percentage": 0.0}, {"name": "107 ANGKASANGGA", "votes": 0, "percentage": 0.0}, {"name": "108 TODA AKSYON", "votes": 0, "percentage": 0.0}, {"name": "109 TURISMO", "votes": 0, "percentage": 0.0}, {"name": "110 ABONO", "votes": 0, "percentage": 0.0}, {"name": "111 ASAP NA", "votes": 0, "percentage": 0.0}, {"name": "112 LINGAP", "votes": 0, "percentage": 0.0}, {"name": "113 UNITED FRONTLINERS", "votes": 0, "percentage": 0.0}, {"name": "114 KASAMBAHAY", "votes": 1, "percentage": 0.31}, {"name": "115 TUTOK TO WIN", "votes": 0, "percentage": 0.0}, {"name": "116 AKO OFW", "votes": 0, "percentage": 0.0}, {"name": "117 AGAP", "votes": 3, "percentage": 0.92}, {"name": "118 1TAHANAN", "votes": 0, "percentage": 0.0}, {"name": "119 COOP-NATCCO", "votes": 19, "percentage": 5.85}, {"name": "120 KABAYAN", "votes": 4, "percentage": 1.23}, {"name": "121 1MUNTI", "votes": 0, "percentage": 0.0}, {"name": "122 PINOY WORKERS", "votes": 0, "percentage": 0.0}, {"name": "123 API PARTY", "votes": 0, "percentage": 0.0}, {"name": "124 AKO BISAYA", "votes": 1, "percentage": 0.31}, {"name": "125 KAMALAYAN", "votes": 0, "percentage": 0.0}, {"name": "126 AKO TANOD", "votes": 0, "percentage": 0.0}, {"name": "127 PROBINSYANO AKO", "votes": 7, "percentage": 2.15}, {"name": "128 KABABAIHAN", "votes": 0, "percentage": 0.0}, {"name": "129 RAM", "votes": 0, "percentage": 0.0}, {"name": "130 ALONA", "votes": 0, "percentage": 0.0}, {"name": "131 AKO BICOL", "votes": 2, "percentage": 0.62}, {"name": "132 GP (GALING SA PUSO)", "votes": 0, "percentage": 0.0}, {"name": "133 KAUNLAD PINOY", "votes": 0, "percentage": 0.0}, {"name": "134 ABP", "votes": 0, "percentage": 0.0}, {"name": "135 CWS", "votes": 0, "percentage": 0.0}, {"name": "136 LPGMA", "votes": 0, "percentage": 0.0}, {"name": "137 A TEACHER", "votes": 0, "percentage": 0.0}, {"name": "138 SWERTE", "votes": 0, "percentage": 0.0}, {"name": "139 GABAY", "votes": 0, "percentage": 0.0}, {"name": "140 MALASAKIT@BAYANIHAN", "votes": 0, "percentage": 0.0}, {"name": "141 AKAY NI SOL", "votes": 0, "percentage": 0.0}, {"name": "142 LUNAS", "votes": 0, "percentage": 0.0}, {"name": "143 DIWA", "votes": 0, "percentage": 0.0}, {"name": "144 PINUNO", "votes": 0, "percentage": 0.0}, {"name": "145 PAMILYA MUNA", "votes": 0, "percentage": 0.0}, {"name": "146 BAGONG PILIPINAS", "votes": 0, "percentage": 0.0}, {"name": "147 HUGPONG FEDERAL", "votes": 0, "percentage": 0.0}, {"name": "148 TUPAD", "votes": 0, "percentage": 0.0}, {"name": "149 LAANG KAWAL", "votes": 1, "percentage": 0.31}, {"name": "150 PAMILYA KO", "votes": 0, "percentage": 0.0}, {"name": "151 BBM", "votes": 0, "percentage": 0.0}, {"name": "152 HEAL PH", "votes": 0, "percentage": 0.0}, {"name": "153 ABANG LINGKOD", "votes": 0, "percentage": 0.0}, {"name": "154 MAGSASAKA", "votes": 0, "percentage": 0.0}, {"name": "155 MAHARLIKA", "votes": 0, "percentage": 0.0}, {"name": "156 USWAG ILONGGO", "votes": 0, "percentage": 0.0}]}}], "local": [{"contestCode": "00729002", "contestName": "MEMBER, HOUSE OF REPRESENTATIVES of ILOCOS SUR - SECOND LEGDIST", "statistic": {"overVotes": 2, "underVotes": 13, "validVotes": 443, "obtainedVotes": 377}, "candidates": {"candidates": [{"name": "1. SINGSON, KRISTINE (NPC)", "votes": 309, "percentage": 81.96}, {"name": "2. VERZOSA, ROQUE JR. (IND)", "votes": 68, "percentage": 18.04}]}}, {"contestCode": "00429000", "contestName": "PROVINCIAL GOVERNOR of ILOCOS SUR", "statistic": {"overVotes": 0, "underVotes": 69, "validVotes": 443, "obtainedVotes": 323}, "candidates": {"candidates": [{"name": "1. SINGSON, JERRY (BILEG)", "votes": 323, "percentage": 100.0}]}}, {"contestCode": "00529000", "contestName": "PROVINCIAL VICE-GOVERNOR of ILOCOS SUR", "statistic": {"overVotes": 0, "underVotes": 64, "validVotes": 443, "obtainedVotes": 328}, "candidates": {"candidates": [{"name": "1. SINGSON, RYAN (BILEG)", "votes": 328, "percentage": 100.0}]}}, {"contestCode": "00629002", "contestName": "MEMBER, SANGGUNIANG PANLALAWIGAN of ILOCOS SUR - SECOND PROVDIST", "statistic": {"overVotes": 5, "underVotes": 798, "validVotes": 2215, "obtainedVotes": 1157}, "candidates": {"candidates": [{"name": "1. ABAYA, JUAN JR (IND)", "votes": 112, "percentage": 9.68}, {"name": "2. GIRONELLA, BOY (BILEG)", "votes": 192, "percentage": 16.59}, {"name": "3. MAGGAY, BEN (BILEG)", "votes": 203, "percentage": 17.55}, {"name": "4. SANIDAD, PABLITO JR. (BILEG)", "votes": 238, "percentage": 20.57}, {"name": "5. SINGSON, ERICSON (PFP)", "votes": 240, "percentage": 20.74}, {"name": "6. ZARAGOZA, FAYINNA PILAR(BILEG)", "votes": 172, "percentage": 14.87}]}}, {"contestCode": "00829040", "contestName": "MAYOR of ILOCOS SUR - BURGOS", "statistic": {"overVotes": 0, "underVotes": 29, "validVotes": 443, "obtainedVotes": 363}, "candidates": {"candidates": [{"name": "1. ESCOBAR, ANNABELLE (BILEG)", "votes": 363, "percentage": 100.0}]}}, {"contestCode": "00929040", "contestName": "VICE-MAYOR of ILOCOS SUR - BURGOS", "statistic": {"overVotes": 0, "underVotes": 46, "validVotes": 443, "obtainedVotes": 346}, "candidates": {"candidates": [{"name": "1. BALBALAN, RIO (BILEG)", "votes": 346, "percentage": 100.0}]}}, {"contestCode": "01029040", "contestName": "MEMBER, SANGGUNIANG BAYAN of ILOCOS SUR - BURGOS - LONE DIST", "statistic": {"overVotes": 32, "underVotes": 350, "validVotes": 3544, "obtainedVotes": 2754}, "candidates": {"candidates": [{"name": "1. AYSON, AVIGAEL JOYCE (BILEG)", "votes": 316, "percentage": 11.47}, {"name": "2. BALBALAN, GEROME ARTHUR(BILEG)", "votes": 351, "percentage": 12.75}, {"name": "3. BELEN, CHRISTOPHER (BILEG)", "votes": 322, "percentage": 11.69}, {"name": "4. CARTA, BERTING (IND)", "votes": 51, "percentage": 1.85}, {"name": "5. CARTA, CORNELIO JR (BILEG)", "votes": 207, "percentage": 7.52}, {"name": "6. DEGRACIA, ISABELO JR. (BILEG)", "votes": 312, "percentage": 11.33}, {"name": "7. DIRECTO, JONATHAN (IND)", "votes": 87, "percentage": 3.16}, {"name": "8. ESCOBAR, MARIUS (BILEG)", "votes": 321, "percentage": 11.66}, {"name": "9. FABRIGAS, NANDING (BILEG)", "votes": 328, "percentage": 11.91}, {"name": "10. ORTEGA, JOHN (IND)", "votes": 251, "percentage": 9.11}, {"name": "11. REYES, OMPONG (BILEG)", "votes": 208, "percentage": 7.55}]}}]}