{"totalErReceived": 100.0, "information": {"machineId": "05130004", "location": "REGION V, ALBAY, PIO DURAN, CARATAGAN", "votingCenter": "CARATAGAN, PIODURAN, ALBAY", "precinctId": "05130004", "precinctInCluster": "0007A, 0008A, 0008B, 0009A, 0009B", "abstentions": 1, "numberOfRegisteredVoters": 983, "numberOfActuallyVoters": 841, "numberOfValidBallot": 841, "turnout": 85.55}, "national": [{"contestCode": "00399000", "contestName": "SENATOR of PHILIPPINES", "statistic": {"overVotes": 192, "underVotes": 4529, "validVotes": 11796, "obtainedVotes": 5371}, "candidates": {"candidates": [{"name": "1. ABALOS, BENHUR (PFP)", "votes": 117, "percentage": 2.18}, {"name": "2. ADONIS, JEROME (MKBYN)", "votes": 14, "percentage": 0.26}, {"name": "3. AMAD, WILSON (IND)", "votes": 9, "percentage": 0.17}, {"name": "4. ANDAMO, NARS ALYN (MKBYN)", "votes": 14, "percentage": 0.26}, {"name": "5. AQUINO, BAM (KNP)", "votes": 420, "percentage": 7.82}, {"name": "6. ARAMBULO, RONNEL (MKBYN)", "votes": 49, "percentage": 0.91}, {"name": "7. ARELLANO, ERNESTO (KTPNAN)", "votes": 11, "percentage": 0.2}, {"name": "8. BALLON, ROBERTO (IND)", "votes": 37, "percentage": 0.69}, {"name": "9. BINAY, ABBY (NPC)", "votes": 193, "percentage": 3.59}, {"name": "10. BONDOC, JIMMY (PDPLBN)", "votes": 42, "percentage": 0.78}, {"name": "11. BONG REVILLA,RAMON, JR.(LAKAS)", "votes": 174, "percentage": 3.24}, {"name": "12. BOSITA, COLONEL (IND)", "votes": 172, "percentage": 3.2}, {"name": "13. BROSAS, ARLENE (MKBYN)", "votes": 56, "percentage": 1.04}, {"name": "14. CABONEGRO, ROY (DPP)", "votes": 7, "percentage": 0.13}, {"name": "15. CAPUYAN, ALLEN (PPP)", "votes": 8, "percentage": 0.15}, {"name": "16. CASI\u00d1O, TEDDY (MKBYN)", "votes": 60, "percentage": 1.12}, {"name": "17. CASTRO, TEACHER FRANCE (MKBYN)", "votes": 67, "percentage": 1.25}, {"name": "18. CAYETANO, PIA (NP)", "votes": 216, "percentage": 4.02}, {"name": "19. D'ANGELO, DAVID (BUNYOG)", "votes": 6, "percentage": 0.11}, {"name": "20. DE ALBAN,ATTORNEY ANGELO (IND)", "votes": 23, "percentage": 0.43}, {"name": "21. DE GUZMAN, KA LEODY (PLM)", "votes": 75, "percentage": 1.4}, {"name": "22. DELA ROSA, BATO (PDPLBN)", "votes": 134, "percentage": 2.49}, {"name": "23. DORINGO, NANAY MIMI (MKBYN)", "votes": 14, "percentage": 0.26}, {"name": "24. ESCOBAL, ARNEL (PM)", "votes": 21, "percentage": 0.39}, {"name": "25. ESPIRITU, LUKE (PLM)", "votes": 102, "percentage": 1.9}, {"name": "26. FLORANDA, MODY PISTON (MKBYN)", "votes": 17, "percentage": 0.32}, {"name": "27. GAMBOA, MARC LOUIE (IND)", "votes": 8, "percentage": 0.15}, {"name": "28. GO, BONG GO    (PDPLBN)", "votes": 202, "percentage": 3.76}, {"name": "29. GONZALES, NORBERTO (PDSP)", "votes": 19, "percentage": 0.35}, {"name": "30. HINLO, JAYVEE (PDPLBN)", "votes": 28, "percentage": 0.52}, {"name": "31. HONASAN, GRINGO (RP)", "votes": 109, "percentage": 2.03}, {"name": "32. JOSE, RELLY JR. (KBL)", "votes": 8, "percentage": 0.15}, {"name": "33. LACSON, PING (IND)", "votes": 224, "percentage": 4.17}, {"name": "34. LAMBINO,  RAUL  (PDPLBN)", "votes": 34, "percentage": 0.63}, {"name": "35. LAPID, LITO (NPC)", "votes": 201, "percentage": 3.74}, {"name": "36. LEE, MANOY WILBERT (AKSYON)", "votes": 12, "percentage": 0.22}, {"name": "37. LIDASAN, AMIRAH (MKBYN)", "votes": 6, "percentage": 0.11}, {"name": "38. MARCOLETA, RODANTE (IND)", "votes": 90, "percentage": 1.68}, {"name": "39. MARCOS, IMEE R. (NP)", "votes": 112, "percentage": 2.09}, {"name": "40. MARQUEZ, NORMAN (IND)", "votes": 20, "percentage": 0.37}, {"name": "41. MARTINEZ, ERIC (IND)", "votes": 9, "percentage": 0.17}, {"name": "42. MATA, DOC MARITES (IND)", "votes": 36, "percentage": 0.67}, {"name": "43. MATULA,  ATTY.  SONNY (WPP)", "votes": 54, "percentage": 1.01}, {"name": "44. MAZA, LIZA (MKBYN)", "votes": 49, "percentage": 0.91}, {"name": "45. MENDOZA, HEIDI (IND)", "votes": 108, "percentage": 2.01}, {"name": "46. MONTEMAYOR,  JOEY  (IND)", "votes": 16, "percentage": 0.3}, {"name": "47. MUSTAPHA, SUBAIR (WPP)", "votes": 6, "percentage": 0.11}, {"name": "48. OLIVAR, JOSE JESSIE (IND)", "votes": 7, "percentage": 0.13}, {"name": "49. ONG, DOC WILLIE (AKSYON)", "votes": 118, "percentage": 2.2}, {"name": "50. PACQUIAO, MANNY PACMAN (PFP)", "votes": 166, "percentage": 3.09}, {"name": "51. PANGILINAN, KIKO (LP)", "votes": 291, "percentage": 5.42}, {"name": "52. QUERUBIN,  ARIEL PORFIRIO (NP)", "votes": 51, "percentage": 0.95}, {"name": "53. QUIBOLOY, APOLLO (IND)", "votes": 23, "percentage": 0.43}, {"name": "54. RAMOS, DANILO (MKBYN)", "votes": 48, "percentage": 0.89}, {"name": "55. REVILLAME, WILLIE WIL (IND)", "votes": 139, "percentage": 2.59}, {"name": "56. RODRIGUEZ, ATTY. VIC (IND)", "votes": 41, "percentage": 0.76}, {"name": "57. SAHIDULLA, NUR-ANA (IND)", "votes": 4, "percentage": 0.07}, {"name": "58. SALVADOR, PHILLIP IPE (PDPLBN)", "votes": 52, "percentage": 0.97}, {"name": "59. SOTTO, TITO (NPC)", "votes": 213, "percentage": 3.97}, {"name": "60. TAPADO, MICHAEL BONGBONG (PM)", "votes": 8, "percentage": 0.15}, {"name": "61. TOLENTINO, FRANCIS TOL (PFP)", "votes": 149, "percentage": 2.77}, {"name": "62. TULFO, BEN BITAG (IND)", "votes": 212, "percentage": 3.95}, {"name": "63. TULFO, ERWIN (LAKAS)", "votes": 276, "percentage": 5.14}, {"name": "64. VALBUENA, MAR MANIBELA (IND)", "votes": 17, "percentage": 0.32}, {"name": "65. VERCELES, LEANDRO (IND)", "votes": 4, "percentage": 0.07}, {"name": "66. VILLAR, CAMILLE (NP)", "votes": 143, "percentage": 2.66}]}}, {"contestCode": "01199000", "contestName": "PARTY LIST of PHILIPPINES", "statistic": {"overVotes": 76, "underVotes": 266, "validVotes": 983, "obtainedVotes": 499}, "candidates": {"candidates": [{"name": "1 4PS", "votes": 20, "percentage": 4.01}, {"name": "2 PPP", "votes": 0, "percentage": 0.0}, {"name": "3 FPJ PANDAY BAYANIHAN", "votes": 3, "percentage": 0.6}, {"name": "4 KABATAAN", "votes": 4, "percentage": 0.8}, {"name": "5 DUTERTE YOUTH", "votes": 9, "percentage": 1.8}, {"name": "6 ML", "votes": 15, "percentage": 3.01}, {"name": "7 PBBM", "votes": 0, "percentage": 0.0}, {"name": "8 P3PWD", "votes": 1, "percentage": 0.2}, {"name": "9 MURANG KURYENTE", "votes": 1, "percentage": 0.2}, {"name": "10 BICOL SARO", "votes": 19, "percentage": 3.81}, {"name": "11 IPATUPAD", "votes": 1, "percentage": 0.2}, {"name": "12 PATROL", "votes": 0, "percentage": 0.0}, {"name": "13 JUAN PINOY", "votes": 0, "percentage": 0.0}, {"name": "14 ARTE", "votes": 0, "percentage": 0.0}, {"name": "15 WIFI", "votes": 1, "percentage": 0.2}, {"name": "16 MAAGAP", "votes": 0, "percentage": 0.0}, {"name": "17 UNITED SENIOR CITIZENS", "votes": 4, "percentage": 0.8}, {"name": "18 EPANAW SAMBAYANAN", "votes": 0, "percentage": 0.0}, {"name": "19 AKO PADAYON", "votes": 0, "percentage": 0.0}, {"name": "20 TUCP", "votes": 0, "percentage": 0.0}, {"name": "21 ACT TEACHERS", "votes": 6, "percentage": 1.2}, {"name": "22 1PACMAN", "votes": 0, "percentage": 0.0}, {"name": "23 TGP", "votes": 2, "percentage": 0.4}, {"name": "24 DUMPER PTDA", "votes": 0, "percentage": 0.0}, {"name": "25 ANAKALUSUGAN", "votes": 0, "percentage": 0.0}, {"name": "26 AKSYON DAPAT", "votes": 0, "percentage": 0.0}, {"name": "27 BHW", "votes": 5, "percentage": 1.0}, {"name": "28 SULONG DIGNIDAD", "votes": 0, "percentage": 0.0}, {"name": "29 BATANG QUIAPO", "votes": 16, "percentage": 3.21}, {"name": "30 PBA", "votes": 0, "percentage": 0.0}, {"name": "31 GILAS", "votes": 1, "percentage": 0.2}, {"name": "32 AKO ILOCANO AKO", "votes": 0, "percentage": 0.0}, {"name": "33 PAMILYANG MAGSASAKA", "votes": 0, "percentage": 0.0}, {"name": "34 CLICK PARTY", "votes": 0, "percentage": 0.0}, {"name": "35 ABANTE BISDAK", "votes": 0, "percentage": 0.0}, {"name": "36 MANILA TEACHERS", "votes": 2, "percentage": 0.4}, {"name": "37 PAMANA", "votes": 0, "percentage": 0.0}, {"name": "38 NANAY", "votes": 0, "percentage": 0.0}, {"name": "39 KM NGAYON NA", "votes": 0, "percentage": 0.0}, {"name": "40 BABAE AKO", "votes": 2, "percentage": 0.4}, {"name": "41 ARISE", "votes": 0, "percentage": 0.0}, {"name": "42 MAGDALO", "votes": 2, "percentage": 0.4}, {"name": "43 APEC", "votes": 0, "percentage": 0.0}, {"name": "44 MAGBUBUKID", "votes": 0, "percentage": 0.0}, {"name": "45 SSS-GSIS PENSYONADO", "votes": 0, "percentage": 0.0}, {"name": "46 GABRIELA", "votes": 0, "percentage": 0.0}, {"name": "47 TINGOG", "votes": 1, "percentage": 0.2}, {"name": "48 APAT-DAPAT", "votes": 0, "percentage": 0.0}, {"name": "49 AHON MAHIRAP", "votes": 0, "percentage": 0.0}, {"name": "50 UGB", "votes": 4, "percentage": 0.8}, {"name": "51 AKBAYAN", "votes": 26, "percentage": 5.21}, {"name": "52 AGIMAT", "votes": 1, "percentage": 0.2}, {"name": "53 PHILRECA", "votes": 1, "percentage": 0.2}, {"name": "54 KAPUSO PM", "votes": 1, "percentage": 0.2}, {"name": "55 ILOCANO DEFENDERS", "votes": 0, "percentage": 0.0}, {"name": "56 1-RIDER PARTY-LIST", "votes": 9, "percentage": 1.8}, {"name": "57 TICTOK", "votes": 0, "percentage": 0.0}, {"name": "59 BAYAN MUNA", "votes": 1, "percentage": 0.2}, {"name": "60 ANG PROBINSIYANO", "votes": 18, "percentage": 3.61}, {"name": "61 BANAT", "votes": 0, "percentage": 0.0}, {"name": "62 SBP", "votes": 0, "percentage": 0.0}, {"name": "63 BUHAY", "votes": 1, "percentage": 0.2}, {"name": "64 TULUNGAN TAYO", "votes": 0, "percentage": 0.0}, {"name": "65 SAGIP", "votes": 5, "percentage": 1.0}, {"name": "66 BTS BAYANING TSUPER", "votes": 1, "percentage": 0.2}, {"name": "67 VENDORS", "votes": 4, "percentage": 0.8}, {"name": "68 ACT-CIS", "votes": 14, "percentage": 2.81}, {"name": "69 AKTIBONG KAAGAPAY", "votes": 1, "percentage": 0.2}, {"name": "70 ASENSO PINOY", "votes": 0, "percentage": 0.0}, {"name": "71 SOLO PARENTS", "votes": 2, "percentage": 0.4}, {"name": "72 ANG KOMADRONA", "votes": 1, "percentage": 0.2}, {"name": "73 PROMDI", "votes": 0, "percentage": 0.0}, {"name": "74 PUSONG PINOY", "votes": 1, "percentage": 0.2}, {"name": "75 KUSUG TAUSUG", "votes": 0, "percentage": 0.0}, {"name": "76 DAMAYANG FILIPINO", "votes": 0, "percentage": 0.0}, {"name": "77 MPBL", "votes": 1, "percentage": 0.2}, {"name": "78 ANGAT", "votes": 2, "percentage": 0.4}, {"name": "79 KALINGA", "votes": 2, "percentage": 0.4}, {"name": "80 BOSES PARTY-LIST", "votes": 3, "percentage": 0.6}, {"name": "81 ARANGKADA PILIPINO", "votes": 0, "percentage": 0.0}, {"name": "82 AANGAT TAYO", "votes": 16, "percentage": 3.21}, {"name": "83 OFW", "votes": 2, "percentage": 0.4}, {"name": "84 BIDA KATAGUMPAY", "votes": 0, "percentage": 0.0}, {"name": "85 KAMANGGAGAWA", "votes": 11, "percentage": 2.2}, {"name": "86 BFF", "votes": 0, "percentage": 0.0}, {"name": "87 BUNYOG", "votes": 3, "percentage": 0.6}, {"name": "88 AGRI", "votes": 0, "percentage": 0.0}, {"name": "89 SENIOR CITIZENS", "votes": 6, "percentage": 1.2}, {"name": "90 4K", "votes": 0, "percentage": 0.0}, {"name": "91 PBP", "votes": 0, "percentage": 0.0}, {"name": "92 ONE COOP", "votes": 0, "percentage": 0.0}, {"name": "93 CIBAC", "votes": 24, "percentage": 4.81}, {"name": "94 BH - BAGONG HENERASYON", "votes": 10, "percentage": 2.0}, {"name": "95 1AGILA", "votes": 0, "percentage": 0.0}, {"name": "96 EDUAKSYON", "votes": 3, "percentage": 0.6}, {"name": "97 ANG TINIG NG SENIORS", "votes": 0, "percentage": 0.0}, {"name": "98 BG PARTY-LIST", "votes": 0, "percentage": 0.0}, {"name": "99 PINOY AKO", "votes": 0, "percentage": 0.0}, {"name": "100 H.E.L.P. PILIPINAS", "votes": 7, "percentage": 1.4}, {"name": "101 HEALTH WORKERS", "votes": 0, "percentage": 0.0}, {"name": "102 PEOPLE'S CHAMP", "votes": 0, "percentage": 0.0}, {"name": "103 AA-KASOSYO PARTY", "votes": 0, "percentage": 0.0}, {"name": "104 SOLID NORTH PARTY", "votes": 0, "percentage": 0.0}, {"name": "105 ABAMIN", "votes": 0, "percentage": 0.0}, {"name": "106 TRABAHO", "votes": 2, "percentage": 0.4}, {"name": "107 ANGKASANGGA", "votes": 0, "percentage": 0.0}, {"name": "108 TODA AKSYON", "votes": 0, "percentage": 0.0}, {"name": "109 TURISMO", "votes": 0, "percentage": 0.0}, {"name": "110 ABONO", "votes": 0, "percentage": 0.0}, {"name": "111 ASAP NA", "votes": 0, "percentage": 0.0}, {"name": "112 LINGAP", "votes": 0, "percentage": 0.0}, {"name": "113 UNITED FRONTLINERS", "votes": 0, "percentage": 0.0}, {"name": "114 KASAMBAHAY", "votes": 0, "percentage": 0.0}, {"name": "115 TUTOK TO WIN", "votes": 0, "percentage": 0.0}, {"name": "116 AKO OFW", "votes": 0, "percentage": 0.0}, {"name": "117 AGAP", "votes": 2, "percentage": 0.4}, {"name": "118 1TAHANAN", "votes": 0, "percentage": 0.0}, {"name": "119 COOP-NATCCO", "votes": 1, "percentage": 0.2}, {"name": "120 KABAYAN", "votes": 3, "percentage": 0.6}, {"name": "121 1MUNTI", "votes": 0, "percentage": 0.0}, {"name": "122 PINOY WORKERS", "votes": 0, "percentage": 0.0}, {"name": "123 API PARTY", "votes": 0, "percentage": 0.0}, {"name": "124 AKO BISAYA", "votes": 0, "percentage": 0.0}, {"name": "125 KAMALAYAN", "votes": 13, "percentage": 2.61}, {"name": "126 AKO TANOD", "votes": 10, "percentage": 2.0}, {"name": "127 PROBINSYANO AKO", "votes": 3, "percentage": 0.6}, {"name": "128 KABABAIHAN", "votes": 0, "percentage": 0.0}, {"name": "129 RAM", "votes": 0, "percentage": 0.0}, {"name": "130 ALONA", "votes": 3, "percentage": 0.6}, {"name": "131 AKO BICOL", "votes": 160, "percentage": 32.06}, {"name": "132 GP (GALING SA PUSO)", "votes": 0, "percentage": 0.0}, {"name": "133 KAUNLAD PINOY", "votes": 0, "percentage": 0.0}, {"name": "134 ABP", "votes": 0, "percentage": 0.0}, {"name": "135 CWS", "votes": 0, "percentage": 0.0}, {"name": "136 LPGMA", "votes": 0, "percentage": 0.0}, {"name": "137 A TEACHER", "votes": 1, "percentage": 0.2}, {"name": "138 SWERTE", "votes": 0, "percentage": 0.0}, {"name": "139 GABAY", "votes": 0, "percentage": 0.0}, {"name": "140 MALASAKIT@BAYANIHAN", "votes": 0, "percentage": 0.0}, {"name": "141 AKAY NI SOL", "votes": 0, "percentage": 0.0}, {"name": "142 LUNAS", "votes": 0, "percentage": 0.0}, {"name": "143 DIWA", "votes": 0, "percentage": 0.0}, {"name": "144 PINUNO", "votes": 0, "percentage": 0.0}, {"name": "145 PAMILYA MUNA", "votes": 0, "percentage": 0.0}, {"name": "146 BAGONG PILIPINAS", "votes": 0, "percentage": 0.0}, {"name": "147 HUGPONG FEDERAL", "votes": 0, "percentage": 0.0}, {"name": "148 TUPAD", "votes": 3, "percentage": 0.6}, {"name": "149 LAANG KAWAL", "votes": 0, "percentage": 0.0}, {"name": "150 PAMILYA KO", "votes": 1, "percentage": 0.2}, {"name": "151 BBM", "votes": 0, "percentage": 0.0}, {"name": "152 HEAL PH", "votes": 0, "percentage": 0.0}, {"name": "153 ABANG LINGKOD", "votes": 0, "percentage": 0.0}, {"name": "154 MAGSASAKA", "votes": 1, "percentage": 0.2}, {"name": "155 MAHARLIKA", "votes": 0, "percentage": 0.0}, {"name": "156 USWAG ILONGGO", "votes": 0, "percentage": 0.0}]}}], "local": [{"contestCode": "00705003", "contestName": "MEMBER, HOUSE OF REPRESENTATIVES of ALBAY - THIRD LEGDIST", "statistic": {"overVotes": 8, "underVotes": 62, "validVotes": 983, "obtainedVotes": 771}, "candidates": {"candidates": [{"name": "1. CABREDO, FERNANDO (NUP)", "votes": 419, "percentage": 54.35}, {"name": "2. SALCEDA, ADRIAN (LAKAS)", "votes": 352, "percentage": 45.65}]}}, {"contestCode": "00405000", "contestName": "PROVINCIAL GOVERNOR of ALBAY", "statistic": {"overVotes": 13, "underVotes": 55, "validVotes": 983, "obtainedVotes": 773}, "candidates": {"candidates": [{"name": "1. ROSAL, NOEL (PDPLBN)", "votes": 390, "percentage": 50.45}, {"name": "2. SALCEDA, JOEY (LAKAS)", "votes": 373, "percentage": 48.25}, {"name": "3. SARA, ROSALER JR. (IND)", "votes": 10, "percentage": 1.29}]}}, {"contestCode": "00505000", "contestName": "PROVINCIAL VICE-GOVERNOR of ALBAY", "statistic": {"overVotes": 15, "underVotes": 140, "validVotes": 983, "obtainedVotes": 686}, "candidates": {"candidates": [{"name": "1. ALEGRE, JUN (PDPLBN)", "votes": 220, "percentage": 32.07}, {"name": "2. ARANDIA, TE (IND)", "votes": 125, "percentage": 18.22}, {"name": "3. CO, DIDAY (LAKAS)", "votes": 337, "percentage": 49.13}, {"name": "4. GOYENA, GIL (WPP)", "votes": 4, "percentage": 0.58}]}}, {"contestCode": "00605003", "contestName": "MEMBER, SANGGUNIANG PANLALAWIGAN of ALBAY - THIRD PROVDIST", "statistic": {"overVotes": 16, "underVotes": 1506, "validVotes": 3932, "obtainedVotes": 1842}, "candidates": {"candidates": [{"name": "1. ARANDIA, BRAYAN (LAKAS)", "votes": 382, "percentage": 20.74}, {"name": "2. BORJA, HERBERT (PFP)", "votes": 170, "percentage": 9.23}, {"name": "3. LAUTA, RAMONITO (IND)", "votes": 10, "percentage": 0.54}, {"name": "4. MADRID, CLARA (IND)", "votes": 60, "percentage": 3.26}, {"name": "5. MARONILLA, DAS (LAKAS)", "votes": 150, "percentage": 8.14}, {"name": "6. PERALTA, GINA (NUP)", "votes": 349, "percentage": 18.95}, {"name": "7. RELUYA, PRIME (PDPLBN)", "votes": 40, "percentage": 2.17}, {"name": "8. RIBAYA, MANNY (LAKAS)", "votes": 257, "percentage": 13.95}, {"name": "9. SALCEDA, CONGCONG (LAKAS)", "votes": 424, "percentage": 23.02}]}}, {"contestCode": "00805130", "contestName": "MAYOR of ALBAY - PIO DURAN", "statistic": {"overVotes": 2, "underVotes": 22, "validVotes": 983, "obtainedVotes": 817}, "candidates": {"candidates": [{"name": "1. ARANDIA, VANGIE (LAKAS)", "votes": 295, "percentage": 36.11}, {"name": "2. BAZAR-GURAT, ATEKAP BBGHIE NUP", "votes": 520, "percentage": 63.65}, {"name": "3. BONDE, SIR BONDE (IND)", "votes": 2, "percentage": 0.24}]}}, {"contestCode": "00905130", "contestName": "VICE-MAYOR of ALBAY - PIO DURAN", "statistic": {"overVotes": 2, "underVotes": 78, "validVotes": 983, "obtainedVotes": 761}, "candidates": {"candidates": [{"name": "1. APULI, DABA (LAKAS)", "votes": 240, "percentage": 31.54}, {"name": "2. CALLOPE, ITAY (NUP)", "votes": 521, "percentage": 68.46}]}}, {"contestCode": "01005130", "contestName": "MEMBER, SANGGUNIANG BAYAN of ALBAY - PIO DURAN - LONE DIST", "statistic": {"overVotes": 272, "underVotes": 1567, "validVotes": 7864, "obtainedVotes": 4889}, "candidates": {"candidates": [{"name": "1. ALANO, BONG (NUP)", "votes": 350, "percentage": 7.16}, {"name": "2. ANTIADO, LHEY (PFP)", "votes": 165, "percentage": 3.37}, {"name": "3. ARIATE, BUNOY (LAKAS)", "votes": 206, "percentage": 4.21}, {"name": "4. BARNIDO, BON (LAKAS)", "votes": 265, "percentage": 5.42}, {"name": "5. DE LUNA, PENDOY (NUP)", "votes": 385, "percentage": 7.87}, {"name": "6. HUBILLA, BEMBOT (NUP)", "votes": 338, "percentage": 6.91}, {"name": "7. LAGUILLES-AQUINO, AIREN (NUP)", "votes": 194, "percentage": 3.97}, {"name": "8. LIM, MARIO (NUP)", "votes": 64, "percentage": 1.31}, {"name": "9. LLONA, ROMY (IND)", "votes": 53, "percentage": 1.08}, {"name": "10. MALGAPO, MARY JUNE (LAKAS)", "votes": 298, "percentage": 6.1}, {"name": "11. MANALLO, RANILO (NUP)", "votes": 183, "percentage": 3.74}, {"name": "12. MOYA, KAREN JOY (LAKAS)", "votes": 210, "percentage": 4.3}, {"name": "13. NAPA, MERS (LAKAS)", "votes": 486, "percentage": 9.94}, {"name": "14. ORAA, GLENN SR. (NUP)", "votes": 274, "percentage": 5.6}, {"name": "15. ORO, DO (IND)", "votes": 67, "percentage": 1.37}, {"name": "16. PACLIBAR, AYING (IND)", "votes": 149, "percentage": 3.05}, {"name": "17. PANEN, ARONFERNANDEZ (IND)", "votes": 18, "percentage": 0.37}, {"name": "18. POLLOSO, JESS (LAKAS)", "votes": 226, "percentage": 4.62}, {"name": "19. QUIROZ, MARVIN APPAMP (LAKAS)", "votes": 327, "percentage": 6.69}, {"name": "20. RIVERA, VIN (IND)", "votes": 57, "percentage": 1.17}, {"name": "21. SAMAR, GHIE (LAKAS)", "votes": 294, "percentage": 6.01}, {"name": "22. SORIA, ATE PARS (NUP)", "votes": 190, "percentage": 3.89}, {"name": "23. TAN, BOK (IND)", "votes": 90, "percentage": 1.84}]}}]}